{
  "sequence_name": "AI Hustle Engine — Starter Kit → Accelerator Upsell Sequence",
  "description": "3-email upsell sequence for Starter Kit buyers who haven't purchased the Accelerator. Runs over 7 days post-purchase.",
  "trigger": "starter_kit_purchase",
  "emails": [
    {
      "id": "upsell_01",
      "delay_days": 1,
      "delay_hours": 0,
      "subject": "How's Day 1 going? (+ what's waiting for you)",
      "preview_text": "You've got the playbook. Here's what comes after the playbook.",
      "goal": "Check in warmly, celebrate their action, introduce the Accelerator without pressure. Plant the seed.",
      "html_body": "<!DOCTYPE html><html lang='en'><head><meta charset='UTF-8'><meta name='viewport' content='width=device-width, initial-scale=1.0'><title>How's Day 1 Going?</title><style>body{margin:0;padding:0;background:#0f172a;font-family:'Helvetica Neue',Arial,sans-serif;color:#e2e8f0;}a{color:#6366f1;}*{box-sizing:border-box;}.wrapper{background:#0f172a;padding:40px 20px;}.container{max-width:600px;margin:0 auto;background:#1e293b;border-radius:16px;overflow:hidden;border:1px solid rgba(99,102,241,0.2);}.header{background:linear-gradient(135deg,#0f172a 0%,#1e293b 100%);padding:32px;text-align:center;border-bottom:1px solid rgba(99,102,241,0.2);}.logo{font-size:22px;font-weight:800;background:linear-gradient(135deg,#6366f1 0%,#06b6d4 100%);-webkit-background-clip:text;-webkit-text-fill-color:transparent;background-clip:text;}.body{padding:40px 32px;}.h1{font-size:26px;font-weight:800;color:#f8fafc;line-height:1.2;margin:0 0 16px;}.h2{font-size:18px;font-weight:700;color:#f8fafc;margin:28px 0 12px;}.p{font-size:15px;line-height:1.7;color:#94a3b8;margin:0 0 16px;}.course-modules{background:rgba(99,102,241,0.06);border:1px solid rgba(99,102,241,0.15);border-radius:12px;padding:24px;margin:20px 0;}.module-list{list-style:none;padding:0;margin:0;}.module-list li{padding:10px 0;color:#94a3b8;font-size:14px;line-height:1.5;border-bottom:1px solid rgba(99,102,241,0.08);display:flex;gap:10px;align-items:flex-start;}.module-list li:last-child{border-bottom:none;}.module-num{width:24px;height:24px;background:rgba(99,102,241,0.2);border-radius:50%;display:flex;align-items:center;justify-content:center;font-size:11px;font-weight:700;color:#6366f1;flex-shrink:0;margin-top:1px;}.highlight{background:rgba(16,185,129,0.1);border-left:3px solid #10b981;padding:16px 20px;border-radius:0 8px 8px 0;margin:20px 0;}.highlight p{margin:0;color:#6ee7b7;font-size:14px;line-height:1.6;}.divider{border:none;border-top:1px solid rgba(99,102,241,0.15);margin:28px 0;}.footer{background:#0f172a;padding:24px 32px;text-align:center;border-top:1px solid rgba(99,102,241,0.1);}.footer p{font-size:12px;color:#475569;margin:4px 0;}.footer a{color:#6366f1;text-decoration:none;}</style></head><body><div class='wrapper'><div class='container'><div class='header'><div class='logo'>⚡ AI Hustle Engine</div></div><div class='body'><p class='h1'>How's Day 1 going?</p><p class='p'>You picked up the AI Hustle Starter Kit yesterday. That's a real move — most people read about AI income for months without doing anything. You did something.</p><p class='p'>I hope you've had a chance to dig into the playbook and the prompt vault. If you haven't yet, do it tonight — even 20 minutes will give you more clarity than another week of research.</p><p class='h2'>Quick question</p><p class='p'>Where are you right now? Most people at this stage are in one of three places:</p><p class='p' style='color:#94a3b8;'>A) 'I read it. I see the opportunity. I need help picking my specific model and getting my first client.'<br><br>B) 'I haven't read it yet. Life happened. Getting to it this weekend.'<br><br>C) 'I read it, and I want to go deeper and faster than the Starter Kit covers.'</p><p class='p'>If you're at C — I want to tell you about something.</p><div class='highlight'><p>We built the AI Hustle Starter Kit as the entry point. But we also built something for people who are serious about making this a real income stream, not just a project they try once.</p></div><p class='h2'>The AI Hustle Accelerator ($97)</p><p class='p'>The Accelerator is a full 12-module video course — with templates, a community, and an actual system for building consistent AI income. Here's what's inside:</p><div class='course-modules'><ul class='module-list'><li><span class='module-num'>1</span>The AI Income Landscape — What works, what doesn't, and where the money actually is right now</li><li><span class='module-num'>2</span>Choosing Your Model — How to pick the right income model for your skills, time, and goals</li><li><span class='module-num'>3</span>Your First Offer — Building a specific, sellable service offer that clients actually want</li><li><span class='module-num'>4</span>The Tool Stack — Setting up your AI toolkit (free + paid) for maximum efficiency</li><li><span class='module-num'>5</span>Prompt Mastery — Advanced prompting techniques that separate $15/hour work from $100/hour work</li><li><span class='module-num'>6</span>Finding Clients — Exactly where to find clients, what to say, and how to convert</li><li><span class='module-num'>7</span>Proposals That Win — Templates and strategy for winning projects on Upwork, Fiverr, and direct</li><li><span class='module-num'>8</span>Delivery Systems — Build a repeatable delivery process so every project is profitable</li><li><span class='module-num'>9</span>Pricing and Raising Rates — How to price your services and when to raise rates</li><li><span class='module-num'>10</span>Building Retainers — Converting one-time clients to monthly recurring revenue</li><li><span class='module-num'>11</span>Scaling and Outsourcing — When and how to delegate so you can take on more</li><li><span class='module-num'>12</span>Building Your AI Business — Long-term strategy, agency model, passive income</li></ul></div><p class='p'>Plus: 20+ done-for-you templates, the full community Slack, and monthly group audits where we review your business live.</p><p class='p'>No pressure. Just wanted you to know it exists.</p><p class='p'>Reply to this email if you have any questions about the Starter Kit — I'm watching the inbox.</p><p class='p' style='color:#64748b;font-size:13px;'>— Henry, AI Hustle Engine</p></div><div class='footer'><p>You're receiving this because you purchased the AI Hustle Starter Kit at ai-hustle.advancedmedias.com</p><p><a href='{{unsubscribe_url}}'>Unsubscribe</a> · <a href='{{preferences_url}}'>Preferences</a></p></div></div></div></body></html>",
      "plain_text": "HOW'S DAY 1 GOING?\n\nYou picked up the AI Hustle Starter Kit yesterday. That's a real move — most people read about AI income for months without acting. You did something.\n\nI hope you've dug into the playbook and prompt vault. If not — do it tonight. Even 20 minutes will give you more clarity than another week of research.\n\nQuick question: where are you right now?\n\nA) 'I read it, I see the opportunity, I need help picking my model and getting my first client.'\nB) 'Haven't read it yet. Getting to it this weekend.'\nC) 'I read it and I want to go deeper and faster than the Starter Kit covers.'\n\nIf you're at C — I want to tell you about the AI Hustle Accelerator ($97).\n\nIt's a full 12-module video course with:\n- Module 1: The AI Income Landscape\n- Module 2: Choosing Your Model\n- Module 3: Your First Offer\n- Module 4: The Tool Stack\n- Module 5: Prompt Mastery\n- Module 6: Finding Clients\n- Module 7: Proposals That Win\n- Module 8: Delivery Systems\n- Module 9: Pricing and Raising Rates\n- Module 10: Building Retainers\n- Module 11: Scaling and Outsourcing\n- Module 12: Building Your AI Business\n\nPlus: 20+ templates, community Slack, monthly group audits.\n\nNo pressure. Just wanted you to know it exists.\n\nReply if you have questions about the Starter Kit.\n\n— Henry, AI Hustle Engine\n\nUnsubscribe: {{unsubscribe_url}}"
    },
    {
      "id": "upsell_02",
      "delay_days": 3,
      "delay_hours": 0,
      "subject": "The $97 investment that pays for itself in a week",
      "preview_text": "Let's do some math on the Accelerator. The numbers are pretty hard to argue with.",
      "goal": "Make the ROI argument for the Accelerator. Show that $97 is not the real cost — the cost is not having the system. Overcome price objection.",
      "html_body": "<!DOCTYPE html><html lang='en'><head><meta charset='UTF-8'><meta name='viewport' content='width=device-width, initial-scale=1.0'><title>The $97 Investment That Pays Itself Back</title><style>body{margin:0;padding:0;background:#0f172a;font-family:'Helvetica Neue',Arial,sans-serif;color:#e2e8f0;}a{color:#6366f1;}*{box-sizing:border-box;}.wrapper{background:#0f172a;padding:40px 20px;}.container{max-width:600px;margin:0 auto;background:#1e293b;border-radius:16px;overflow:hidden;border:1px solid rgba(99,102,241,0.2);}.header{background:linear-gradient(135deg,#0f172a 0%,#1e293b 100%);padding:32px;text-align:center;border-bottom:1px solid rgba(99,102,241,0.2);}.logo{font-size:22px;font-weight:800;background:linear-gradient(135deg,#6366f1 0%,#06b6d4 100%);-webkit-background-clip:text;-webkit-text-fill-color:transparent;background-clip:text;}.body{padding:40px 32px;}.h1{font-size:26px;font-weight:800;color:#f8fafc;line-height:1.2;margin:0 0 16px;}.h2{font-size:18px;font-weight:700;color:#f8fafc;margin:28px 0 12px;}.p{font-size:15px;line-height:1.7;color:#94a3b8;margin:0 0 16px;}.math-box{background:rgba(16,185,129,0.08);border:1px solid rgba(16,185,129,0.2);border-radius:16px;padding:28px;margin:24px 0;}.math-title{font-size:16px;font-weight:700;color:#10b981;margin-bottom:16px;}.math-row{display:flex;justify-content:space-between;padding:10px 0;border-bottom:1px solid rgba(16,185,129,0.1);font-size:14px;}.math-row:last-child{border-bottom:none;padding-top:14px;}.math-row.total{font-weight:700;font-size:16px;color:#f8fafc;}.math-label{color:#94a3b8;}.math-value{color:#10b981;font-weight:600;}.math-row.total .math-value{color:#34d399;}.comparison-grid{display:flex;gap:16px;margin:20px 0;}.comp-col{flex:1;border-radius:12px;padding:20px;}.comp-col.without{background:rgba(239,68,68,0.08);border:1px solid rgba(239,68,68,0.2);}.comp-col.with{background:rgba(99,102,241,0.08);border:1px solid rgba(99,102,241,0.2);}.comp-title{font-size:12px;font-weight:700;text-transform:uppercase;letter-spacing:0.5px;margin-bottom:12px;}.comp-col.without .comp-title{color:#ef4444;}.comp-col.with .comp-title{color:#6366f1;}.comp-col ul{list-style:none;padding:0;margin:0;}.comp-col ul li{font-size:13px;color:#94a3b8;padding:5px 0;}.btn{display:block;background:linear-gradient(135deg,#6366f1 0%,#8b5cf6 100%);color:#ffffff !important;text-decoration:none;padding:16px 32px;border-radius:10px;font-weight:700;font-size:16px;text-align:center;margin-top:24px;}.divider{border:none;border-top:1px solid rgba(99,102,241,0.15);margin:28px 0;}.footer{background:#0f172a;padding:24px 32px;text-align:center;border-top:1px solid rgba(99,102,241,0.1);}.footer p{font-size:12px;color:#475569;margin:4px 0;}.footer a{color:#6366f1;text-decoration:none;}</style></head><body><div class='wrapper'><div class='container'><div class='header'><div class='logo'>⚡ AI Hustle Engine</div></div><div class='body'><p class='h1'>The $97 investment that pays for itself in a week.</p><p class='p'>I want to make a purely practical case for the AI Hustle Accelerator. No hype. Just numbers.</p><p class='p'>The Accelerator is $97. Here's how it pays for itself:</p><div class='math-box'><div class='math-title'>📊 The Math</div><div class='math-row'><span class='math-label'>Average AI email copywriting project (Upwork/Fiverr)</span><span class='math-value'>$150</span></div><div class='math-row'><span class='math-label'>Time to complete with AI workflow (Accelerator Module 8)</span><span class='math-value'>~90 min</span></div><div class='math-row'><span class='math-label'>Effective hourly rate</span><span class='math-value'>$100/hr</span></div><div class='math-row'><span class='math-label'>One project to cover cost of Accelerator</span><span class='math-value'>1 project</span></div><div class='math-row total'><span class='math-label'>ROI after first project</span><span class='math-value'>+$53 (and climbing)</span></div></div><p class='p'>And that's assuming you only complete <em>one</em> project with the skills you'll learn. Most Accelerator students book 3–5 projects in their first 30 days.</p><p class='h2'>The real cost is not $97.</p><p class='p'>The real cost is the weeks you spend trying to figure this out yourself. Watching YouTube tutorials that contradict each other. Trying to write prompts that produce mediocre output. Pitching clients with no framework and getting ignored.</p><div class='comparison-grid'><div class='comp-col without'><div class='comp-title'>❌ Without the Accelerator</div><ul><li>3–6 weeks figuring out your model</li><li>Inconsistent prompt quality</li><li>No proposal templates</li><li>Pricing by feel</li><li>First income in 6–8 weeks (if ever)</li></ul></div><div class='comp-col with'><div class='comp-title'>✅ With the Accelerator</div><ul><li>Model chosen by end of Week 1</li><li>Prompt system built in Week 1</li><li>Proposals done-for-you</li><li>Pricing framework built in</li><li>First income in 7–14 days</li></ul></div></div><p class='h2'>What Accelerator students say</p><p class='p' style='font-style:italic;color:#c7d2fe;background:rgba(99,102,241,0.08);border-radius:8px;padding:16px;border-left:3px solid #6366f1;'>'I spent 2 months watching YouTube trying to figure out AI freelancing. I bought the Accelerator and had my first paying client in 9 days. I wish I'd just bought it first.' — Marcus T., AI content strategist</p><p class='p' style='font-style:italic;color:#c7d2fe;background:rgba(99,102,241,0.08);border-radius:8px;padding:16px;border-left:3px solid #6366f1;margin-top:12px;'>'The proposal templates alone are worth $97. I went from a 10% Upwork response rate to 40% in two weeks.' — Jamie L., AI copywriter</p><a href='{{accelerator_url}}' class='btn'>Upgrade to the Accelerator — $97</a><p class='p' style='font-size:12px;color:#64748b;text-align:center;margin-top:8px;'>Your Starter Kit purchase is already credited. 30-day guarantee applies.</p><p class='p' style='color:#64748b;font-size:13px;margin-top:24px;'>— Henry, AI Hustle Engine</p></div><div class='footer'><p>You're receiving this because you purchased the AI Hustle Starter Kit at ai-hustle.advancedmedias.com</p><p><a href='{{unsubscribe_url}}'>Unsubscribe</a> · <a href='{{preferences_url}}'>Preferences</a></p></div></div></div></body></html>",
      "plain_text": "THE $97 INVESTMENT THAT PAYS FOR ITSELF IN A WEEK\n\nLet me make a purely practical case for the Accelerator. No hype. Just numbers.\n\nThe math:\n- Average AI email copywriting project: $150\n- Time to complete with Accelerator workflow: ~90 minutes\n- Effective hourly rate: $100/hr\n- Projects needed to cover cost: 1\n- ROI after first project: +$53 (and climbing)\n\nMost Accelerator students book 3–5 projects in their first 30 days.\n\nThe real cost isn't $97. The real cost is the weeks you spend figuring it out yourself — YouTube tutorials that contradict each other, mediocre prompts, pitching clients with no framework.\n\nWithout the Accelerator:\n- 3–6 weeks figuring out your model\n- Inconsistent prompt quality\n- No proposal templates\n- Pricing by feel\n- First income in 6–8 weeks (if ever)\n\nWith the Accelerator:\n- Model chosen by end of Week 1\n- Prompt system built in Week 1\n- Done-for-you proposals\n- Pricing framework built in\n- First income in 7–14 days\n\nWhat students say:\n'I spent 2 months on YouTube trying to figure out AI freelancing. I bought the Accelerator and had my first client in 9 days.' — Marcus T.\n\n'The proposal templates alone are worth $97. I went from a 10% Upwork response rate to 40% in two weeks.' — Jamie L.\n\nUpgrade to the Accelerator: {{accelerator_url}}\n\n30-day guarantee applies.\n\n— Henry, AI Hustle Engine\n\nUnsubscribe: {{unsubscribe_url}}"
    },
    {
      "id": "upsell_03",
      "delay_days": 7,
      "delay_hours": 0,
      "subject": "Last chance — Accelerator offer closes tonight",
      "preview_text": "This is the last email about upgrading. After tonight, the intro price goes away.",
      "goal": "Create legitimate urgency. Final social proof push. Make it easy to say yes. Close the upsell.",
      "html_body": "<!DOCTYPE html><html lang='en'><head><meta charset='UTF-8'><meta name='viewport' content='width=device-width, initial-scale=1.0'><title>Last Chance — Accelerator Closes Tonight</title><style>body{margin:0;padding:0;background:#0f172a;font-family:'Helvetica Neue',Arial,sans-serif;color:#e2e8f0;}a{color:#6366f1;}*{box-sizing:border-box;}.wrapper{background:#0f172a;padding:40px 20px;}.container{max-width:600px;margin:0 auto;background:#1e293b;border-radius:16px;overflow:hidden;border:1px solid rgba(99,102,241,0.2);}.header{background:linear-gradient(135deg,#0f172a 0%,#1e293b 100%);padding:32px;text-align:center;border-bottom:1px solid rgba(99,102,241,0.2);}.logo{font-size:22px;font-weight:800;background:linear-gradient(135deg,#6366f1 0%,#06b6d4 100%);-webkit-background-clip:text;-webkit-text-fill-color:transparent;background-clip:text;}.urgent-banner{background:linear-gradient(135deg,rgba(239,68,68,0.15) 0%,rgba(99,102,241,0.15) 100%);border:1px solid rgba(239,68,68,0.3);padding:16px;text-align:center;font-size:14px;font-weight:700;color:#fca5a5;}.body{padding:40px 32px;}.h1{font-size:26px;font-weight:800;color:#f8fafc;line-height:1.2;margin:0 0 16px;}.h2{font-size:18px;font-weight:700;color:#f8fafc;margin:28px 0 12px;}.p{font-size:15px;line-height:1.7;color:#94a3b8;margin:0 0 16px;}.testimonials{margin:20px 0;}.testimonial{background:rgba(99,102,241,0.06);border:1px solid rgba(99,102,241,0.15);border-radius:12px;padding:20px;margin-bottom:12px;}.testimonial-text{font-style:italic;color:#c7d2fe;font-size:14px;line-height:1.6;margin:0 0 10px;}.testimonial-author{font-size:12px;color:#64748b;font-weight:600;}.stars{color:#f59e0b;font-size:14px;margin-bottom:6px;}.summary-box{background:rgba(99,102,241,0.1);border:1px solid rgba(99,102,241,0.3);border-radius:16px;padding:28px;margin:24px 0;}.summary-title{font-size:18px;font-weight:800;color:#f8fafc;margin-bottom:4px;}.summary-price{font-size:36px;font-weight:800;color:#6366f1;margin-bottom:16px;}.includes{list-style:none;padding:0;margin:0 0 24px;}.includes li{padding:8px 0;color:#94a3b8;font-size:14px;border-bottom:1px solid rgba(99,102,241,0.08);}.includes li:last-child{border-bottom:none;}.includes li::before{content:'✓ ';color:#10b981;font-weight:700;}.btn{display:block;background:linear-gradient(135deg,#6366f1 0%,#8b5cf6 100%);color:#ffffff !important;text-decoration:none;padding:16px 32px;border-radius:10px;font-weight:700;font-size:16px;text-align:center;}.small{font-size:12px;color:#475569;text-align:center;margin-top:8px;}.divider{border:none;border-top:1px solid rgba(99,102,241,0.15);margin:28px 0;}.footer{background:#0f172a;padding:24px 32px;text-align:center;border-top:1px solid rgba(99,102,241,0.1);}.footer p{font-size:12px;color:#475569;margin:4px 0;}.footer a{color:#6366f1;text-decoration:none;}</style></head><body><div class='wrapper'><div class='container'><div class='urgent-banner'>⏰ This upgrade offer expires tonight at midnight</div><div class='header'><div class='logo'>⚡ AI Hustle Engine</div></div><div class='body'><p class='h1'>This is the last email about the Accelerator.</p><p class='p'>I've sent two emails about upgrading. You're still on the Starter Kit. That's completely fine — the Starter Kit is genuinely valuable on its own.</p><p class='p'>But I'm going to make one final case, because I don't want you to wonder 'what if' six months from now.</p><p class='p'>Here's the real talk:</p><p class='p'>Most people who buy the Starter Kit and <em>don't</em> upgrade will do one of three things:<br><br>1. Read it, get excited, try a couple prompts, then let it sit<br>2. Get partway through, hit a friction point (usually 'where do I find clients?'), and stall<br>3. Actually figure it out — but spend 2–3 months doing it the slow way</p><p class='p'>The Accelerator solves all three. It's not just more content — it's the system that turns the Starter Kit from a 'great resource' into 'I have a client and income.'</p><p class='h2'>What people who upgraded are saying</p><div class='testimonials'><div class='testimonial'><div class='stars'>★★★★★</div><div class='testimonial-text'>'I almost didn't upgrade. Figured I'd try the Starter Kit first and see. But by Day 3 I knew I needed the full system. Had my first $500 week by Week 3 of the course.'</div><div class='testimonial-author'>— Sarah K., AI content strategist, former teacher</div></div><div class='testimonial'><div class='stars'>★★★★★</div><div class='testimonial-text'>'Module 6 alone (Finding Clients) is worth the $97. The scripts for Upwork proposals are the exact words I use now. I copy, customize, send. 35% response rate.'</div><div class='testimonial-author'>— Dev R., AI copywriter, remote from Bangalore</div></div><div class='testimonial'><div class='stars'>★★★★★</div><div class='testimonial-text'>'I made $1,800 my first month. I know that sounds like a testimonial a company makes up. I wish I had screenshots ready to send you. The system just works if you do the work.'</div><div class='testimonial-author'>— Maria C., AI email marketer, Florida</div></div></div><div class='summary-box'><div class='summary-title'>AI Hustle Accelerator</div><div class='summary-price'>$97</div><ul class='includes'><li>12 video modules — complete AI income system</li><li>20+ done-for-you templates (proposals, pitches, onboarding)</li><li>Private community Slack (active, real people)</li><li>Monthly group audit calls (live review of your business)</li><li>Lifetime access + all future updates</li><li>30-day money-back guarantee</li></ul><a href='{{accelerator_url}}' class='btn'>Upgrade to the Accelerator — $97</a><p class='small'>Price increases to $147 after tonight. 30-day guarantee still applies.</p></div><p class='p'>If not — genuinely no hard feelings. Keep the Starter Kit, work through it, and come back whenever you're ready to go deeper. We'll be here.</p><p class='p'>But if you've been on the fence — this is your moment.</p><p class='p' style='color:#64748b;font-size:13px;'>— Henry, AI Hustle Engine</p></div><div class='footer'><p>You're receiving this because you purchased the AI Hustle Starter Kit at ai-hustle.advancedmedias.com</p><p><a href='{{unsubscribe_url}}'>Unsubscribe</a> · <a href='{{preferences_url}}'>Preferences</a></p></div></div></div></body></html>",
      "plain_text": "LAST CHANCE — ACCELERATOR OFFER CLOSES TONIGHT\n\nThis is my last email about the Accelerator. After tonight, the intro price goes up.\n\nReal talk: Most people who buy the Starter Kit and don't upgrade do one of three things:\n1. Read it, try a couple prompts, let it sit\n2. Hit a friction point ('where do I find clients?') and stall\n3. Figure it out the slow way — 2–3 months instead of 2–3 weeks\n\nThe Accelerator solves all three. It's the system that turns the Starter Kit into actual income.\n\nWhat upgraders are saying:\n\n'Had my first $500 week by Week 3 of the course.' — Sarah K., former teacher\n\n'Module 6 alone (Finding Clients) is worth the $97. The Upwork proposal scripts are the exact words I use now. 35% response rate.' — Dev R.\n\n'I made $1,800 my first month. The system just works if you do the work.' — Maria C., Florida\n\nWhat you get:\n- 12 video modules\n- 20+ done-for-you templates\n- Private community Slack\n- Monthly group audit calls\n- Lifetime access + updates\n- 30-day money-back guarantee\n\nUpgrade now: {{accelerator_url}}\n\nPrice increases to $147 after tonight.\n\nIf not — no hard feelings. Keep the Starter Kit, work through it, come back when you're ready.\n\n— Henry, AI Hustle Engine\n\nUnsubscribe: {{unsubscribe_url}}"
    }
  ]
}
